tkintermapview/__init__.py
tkintermapview/canvas_button.py
tkintermapview/canvas_path.py
tkintermapview/canvas_polygon.py
tkintermapview/canvas_position_marker.py
tkintermapview/canvas_tile.py
tkintermapview/map_widget.py
tkintermapview/offline_loading.py
tkintermapview/utility_functions.py
tkintermapview-1.29.dist-info/LICENSE.txt
tkintermapview-1.29.dist-info/METADATA
tkintermapview-1.29.dist-info/WHEEL
tkintermapview-1.29.dist-info/top_level.txt
tkintermapview-1.29.dist-info/RECORD
