Metadata-Version: 2.1
Name: tkintermapview
Version: 1.29
Summary: A python Tkinter widget to display image tile maps like OpenStreetMap or Satellite Images.
Home-page: https://github.com/TomSchimansky/TkinterMapView
Author: Tom Schimansky
License: Creative Commons Zero v1.0 Universal
Classifier: Operating System :: OS Independent
Classifier: Programming Language :: Python :: 3
Classifier: License :: CC0 1.0 Universal (CC0 1.0) Public Domain Dedication
Requires-Python: >=3.6
License-File: LICENSE.txt
